dmtoolbox/__init__.py
dmtoolbox/appdataGen.py
dmtoolbox/createExeOnC.py
dmtoolbox/exeGenerator.py
dmtoolbox/func.py
dmtoolbox/genJsons.py
dmtoolbox/nginxDefaults.py
dmtoolbox/nginxUtils.py
dmtoolbox/numericFuncs.py
dmtoolbox/osFuncs.py
dmtoolbox/portTools.py
dmtoolbox/regedit.py
dmtoolbox-0.10.dist-info/LICENSE
dmtoolbox-0.10.dist-info/METADATA
dmtoolbox-0.10.dist-info/WHEEL
dmtoolbox-0.10.dist-info/top_level.txt
dmtoolbox-0.10.dist-info/RECORD
